{
  "_cookie_refreshed_at": "2026-04-16T20:30:30Z",
  "csrftoken": "aL5enoYhRk6bgn6g5ZfDrs",
  "datr": "k7Xcaf3c6_bSSwDJPYmAaMaM",
  "dpr": "1",
  "ds_user_id": "34899148734",
  "ig_did": "3DDE48AA-6C7D-4AF2-BBEA-55A583A71076",
  "mid": "ady1kwAEAAG5rwB8zQb9QFKbLyrM",
  "ps_l": "1",
  "ps_n": "1",
  "rur": "\"ATG\\05434899148734\\0541807891910:01feb583e37a6c57e7d0e75847073b537948d16eb77b809cbbc7bd5310a7c58200fcf518\"",
  "sessionid": "34899148734%3Akh7g1klPsd4T8z%3A16%3AAYhJw0cezdubwSQfMMKGe88j_kAo7n-sIP7tCLaavg",
  "wd": "1280x1400"
}
